{
  "id": "2686681",
  "name": "vue-iot",
  "font_family": "iconfont",
  "css_prefix_text": "icon-",
  "description": "硕博物联",
  "glyphs": [
    {
      "icon_id": "297678",
      "name": "文本编辑_填充",
      "font_class": "zanwushuju1",
      "unicode": "e6d4",
      "unicode_decimal": 59092
    },
    {
      "icon_id": "297679",
      "name": "文本编辑",
      "font_class": "zanwushuju2",
      "unicode": "e6d5",
      "unicode_decimal": 59093
    },
    {
      "icon_id": "588347",
      "name": "订购",
      "font_class": "taocandinggou",
      "unicode": "e6cb",
      "unicode_decimal": 59083
    },
    {
      "icon_id": "1132491",
      "name": "左箭头",
      "font_class": "left",
      "unicode": "e647",
      "unicode_decimal": 58951
    },
    {
      "icon_id": "1203711",
      "name": "余额",
      "font_class": "yuechongzhi",
      "unicode": "e608",
      "unicode_decimal": 58888
    },
    {
      "icon_id": "1403074",
      "name": "查询",
      "font_class": "chaxun",
      "unicode": "e632",
      "unicode_decimal": 58930
    },
    {
      "icon_id": "2448136",
      "name": "问题反馈",
      "font_class": "wentifankui",
      "unicode": "e63a",
      "unicode_decimal": 58938
    },
    {
      "icon_id": "6882983",
      "name": "充值记录",
      "font_class": "chongzhijilu",
      "unicode": "e612",
      "unicode_decimal": 58898
    },
    {
      "icon_id": "7708031",
      "name": "右箭头",
      "font_class": "right",
      "unicode": "e61d",
      "unicode_decimal": 58909
    },
    {
      "icon_id": "7734744",
      "name": "实名认证",
      "font_class": "shimingrenzheng",
      "unicode": "e750",
      "unicode_decimal": 59216
    },
    {
      "icon_id": "8988362",
      "name": "智能诊断",
      "font_class": "zhinengzhenduan",
      "unicode": "e617",
      "unicode_decimal": 58903
    },
    {
      "icon_id": "12752688",
      "name": "更新",
      "font_class": "gengxin",
      "unicode": "e626",
      "unicode_decimal": 58918
    },
    {
      "icon_id": "17605441",
      "name": "购买",
      "font_class": "zaixiangoumai",
      "unicode": "e811",
      "unicode_decimal": 59409
    },
    {
      "icon_id": "18375426",
      "name": "喇叭",
      "font_class": "gonggao",
      "unicode": "e614",
      "unicode_decimal": 58900
    },
    {
      "icon_id": "18863066",
      "name": "人",
      "font_class": "yishiming",
      "unicode": "e63d",
      "unicode_decimal": 58941
    },
    {
      "icon_id": "22533640",
      "name": "勾选",
      "font_class": "yijihuo",
      "unicode": "e62c",
      "unicode_decimal": 58924
    },
    {
      "icon_id": "9698213",
      "name": "点点点",
      "font_class": "font-more",
      "unicode": "e667",
      "unicode_decimal": 58983
    },
    {
      "icon_id": "4320337",
      "name": "返回",
      "font_class": "font-left",
      "unicode": "e654",
      "unicode_decimal": 58964
    },
    {
      "icon_id": "9255041",
      "name": "iot 物联网平台",
      "font_class": "iot",
      "unicode": "e916",
      "unicode_decimal": 59670
    }
  ]
}
